fastwork/__init__.py
fastwork/merge-DESKTOP-A38NAQB.py
fastwork/merge.py
fastwork/tools.py
ui/Ui_fastwork.py
ui/Ui_fastwork_merge.py
ui/__init__.py
fastwork-0.0.4.dist-info/LICENSE
fastwork-0.0.4.dist-info/METADATA
fastwork-0.0.4.dist-info/PKG-INFO-DESKTOP-A38NAQB
fastwork-0.0.4.dist-info/SOURCES-DESKTOP-A38NAQB.txt
fastwork-0.0.4.dist-info/WHEEL
fastwork-0.0.4.dist-info/top_level-DESKTOP-A38NAQB.txt
fastwork-0.0.4.dist-info/top_level.txt
fastwork-0.0.4.dist-info/RECORD
