Metadata-Version: 2.1
Name: fastwork
Version: 0.0.4
Summary: an useful tool for ending your boring work
Home-page: https://github.com/xugongli/fastwork.git
Author: soaringsoul
Author-email: 951683309@qq.com
License: UNKNOWN
Platform: UNKNOWN
Classifier: Development Status :: 4 - Beta
Classifier: Environment :: Console
Classifier: Intended Audience :: Developers
Classifier: License :: OSI Approved :: MIT License
Classifier: Operating System :: OS Independent
Classifier: Programming Language :: Python
Classifier: Programming Language :: Python :: 3
Classifier: Programming Language :: Python :: 3.5
Classifier: Programming Language :: Python :: 3.6
Classifier: Programming Language :: Python :: 3.7
Classifier: Programming Language :: Python :: 3.8
Classifier: Programming Language :: Python :: Implementation :: CPython
Classifier: Programming Language :: Python :: Implementation :: PyPy
Classifier: Topic :: Internet :: WWW/HTTP
Classifier: Topic :: Software Development :: Libraries :: Application Frameworks
Classifier: Topic :: Software Development :: Libraries :: Python Modules
Requires-Python: >=3.5
Requires-Dist: xlsxwriter (>=1.2.0)
Requires-Dist: openpyxl (>=3.0.4)
Requires-Dist: pandas (>=1.0.5)
Requires-Dist: xlrd (>=1.2.0)
